python_mini_project/command_dictionary.py
python_mini_project/command_list.py
python_mini_project/core_event.py
python_mini_project/dispatcher.py
python_mini_project/extern.py
python_mini_project/commands/cat.py
python_mini_project/commands/cd.py
python_mini_project/commands/cp.py
python_mini_project/commands/find.py
python_mini_project/commands/grep.py
python_mini_project/commands/head.py
python_mini_project/commands/help.py
python_mini_project/commands/ls.py
python_mini_project/commands/mkdir.py
python_mini_project/commands/mv.py
python_mini_project/commands/pwd.py
python_mini_project/commands/rm.py
python_mini_project/commands/rmdir.py
python_mini_project/commands/sizeof.py
python_mini_project/commands/tail.py
python_mini_project/commands/test_project.py
pyshell_package-1.0.1.dist-info/LICENSE
pyshell_package-1.0.1.dist-info/METADATA
pyshell_package-1.0.1.dist-info/WHEEL
pyshell_package-1.0.1.dist-info/entry_points.txt
pyshell_package-1.0.1.dist-info/top_level.txt
pyshell_package-1.0.1.dist-info/RECORD
