Metadata-Version: 2.1
Name: pyshell-package
Version: 1.0.1
Summary: A rudimentary UNIX-like shell that allows extensibility using custom python modules to implement various features as shell commands.
Home-page: https://git.corp.adobe.com/priyanss/python-mini-project
Author: Samridhi Chaubey
License: MIT
Platform: UNKNOWN
Classifier: License :: OSI Approved :: MIT License
Classifier: Programming Language :: Python :: 3
Classifier: Programming Language :: Python :: 3.6
